.pylintrc
AUTHORS
ChangeLog
LICENSE
MANIFEST.in
README.md
requirements.txt
run_tests.sh
setup.cfg
setup.py
tox.ini
img/demo.gif
img/demo.png
img/download.png
img/list_apps.png
r2flutch/__init__.py
r2flutch/config.py
r2flutch/device.py
r2flutch/io.py
r2flutch/r2frida.py
r2flutch/repl.py
r2flutch/utils.py
r2flutch.egg-info/PKG-INFO
r2flutch.egg-info/SOURCES.txt
r2flutch.egg-info/dependency_links.txt
r2flutch.egg-info/entry_points.txt
r2flutch.egg-info/not-zip-safe
r2flutch.egg-info/pbr.json
r2flutch.egg-info/requires.txt
r2flutch.egg-info/top_level.txt
r2flutch/agent/plugin.js
r2flutch/bin/__init__.py
r2flutch/bin/run.py
requirements/build.txt
requirements/dist.txt
requirements/test.txt
test/Makefile