Metadata-Version: 2.1
Name: r2flutch
Version: 1.0.3
Summary: allows to decrypt iOS applications using r2frida (radare2 and Frida)
Home-page: https://www.0xmurphy.me/
Author: murphy
Author-email: me@0xmurphy.me
License: UNKNOWN
Project-URL: Source, https://github.com/as0ler/r2flutch
Project-URL: Documentation, https://github.com/as0ler/r2flutch
Platform: UNKNOWN
Classifier: Environment :: Console
Classifier: Environment :: MacOS X
Classifier: Environment :: Win32 (MS Windows)
Classifier: License :: OSI Approved
Classifier: Natural Language :: English
Classifier: Operating System :: MacOS :: MacOS X
Classifier: Operating System :: Microsoft :: Windows
Classifier: Operating System :: POSIX
Classifier: Operating System :: POSIX :: BSD
Classifier: Operating System :: POSIX :: Linux
Classifier: Programming Language :: Python :: 3
Classifier: Programming Language :: Python :: 3.8
Classifier: Programming Language :: Python :: 3.9
License-File: LICENSE
